poetry_deps_scanner/__init__.py
poetry_deps_scanner/comment_gitlab.py
poetry_deps_scanner/scan_deps.py
poetry_deps_scanner-2.0.0.post2.dist-info/entry_points.txt
poetry_deps_scanner-2.0.0.post2.dist-info/LICENSE
poetry_deps_scanner-2.0.0.post2.dist-info/WHEEL
poetry_deps_scanner-2.0.0.post2.dist-info/METADATA
poetry_deps_scanner-2.0.0.post2.dist-info/RECORD
