Metadata-Version: 2.1
Name: poetry-deps-scanner
Version: 2.0.0.post2
Summary: Analyse poetry dependencies and comment on gitlab
Home-page: https://github.com/itsolutionsfactory/poetry-deps-scanner/
License: MIT
Keywords: pyhon-poetry,poetry,gitlab,dependencies
Author: Gabriel Augendre
Author-email: gabriel.augendre@itsfactory.fr
Maintainer: Gabriel Augendre
Maintainer-email: gabriel.augendre@itsfactory.fr
Requires-Python: >=3.10,<4
Classifier: Development Status :: 5 - Production/Stable
Classifier: Environment :: Console
Classifier: Intended Audience :: Developers
Classifier: License :: OSI Approved :: MIT License
Classifier: Operating System :: OS Independent
Classifier: Programming Language :: Python :: 3
Classifier: Programming Language :: Python :: 3.10
Classifier: Topic :: Software Development :: Libraries
Classifier: Topic :: Utilities
Requires-Dist: packaging (>=21.3,<22.0)
Requires-Dist: prettytable (>=3.3.0,<4.0.0)
Requires-Dist: pypi-simple (>=0.9.0,<0.10.0)
Requires-Dist: python-gitlab (>=2.6.0)
Requires-Dist: toml (>=0.10.2)
Project-URL: Repository, https://github.com/itsolutionsfactory/poetry-deps-scanner
